synimatic/__init__.py
synimatic-1.0.2.dist-info/licenses/LICENSE
synimatic-1.0.2.dist-info/METADATA
synimatic-1.0.2.dist-info/WHEEL
synimatic-1.0.2.dist-info/top_level.txt
synimatic-1.0.2.dist-info/RECORD
