Metadata-Version: 2.4
Name: synimatic
Version: 1.0.2
Summary: Simple and effective matplotlib animation wrapper
Home-page: https://github.com/jonathan-4a/synimatic
Author: Jonathan Ayalew
Classifier: Development Status :: 5 - Production/Stable
Classifier: Intended Audience :: Developers
Classifier: Intended Audience :: Science/Research
Classifier: License :: OSI Approved :: MIT License
Classifier: Programming Language :: Python :: 3.8
Classifier: Programming Language :: Python :: 3.9
Classifier: Programming Language :: Python :: 3.10
Classifier: Programming Language :: Python :: 3.11
Classifier: Programming Language :: Python :: 3.12
Classifier: Topic :: Scientific/Engineering :: Visualization
Requires-Python: >=3.8
License-File: LICENSE
Requires-Dist: matplotlib>=3.7.0
Requires-Dist: tqdm>=4.66.5
Provides-Extra: jupyter
Requires-Dist: ipython; extra == "jupyter"
Dynamic: author
Dynamic: classifier
Dynamic: description
Dynamic: description-content-type
Dynamic: home-page
Dynamic: license-file
Dynamic: provides-extra
Dynamic: requires-dist
Dynamic: requires-python
Dynamic: summary
